tcurve/__init__.py
tcurve/dash.py
tcurve/utils.py
tcurve-0.1.2.dist-info/licenses/LICENSE
tcurve-0.1.2.dist-info/METADATA
tcurve-0.1.2.dist-info/WHEEL
tcurve-0.1.2.dist-info/top_level.txt
tcurve-0.1.2.dist-info/RECORD
