Metadata-Version: 2.4
Name: tcurve
Version: 0.1.2
Summary: A sleek tool that displays visually appealing progress bars and draws metric based curves in real-time.
Author-email: Seria <zzqsummerai@yeah.net>
License-File: LICENSE
Requires-Dist: numpy
Requires-Dist: pandas
Requires-Dist: matplotlib
Requires-Dist: seaborn
Dynamic: license-file
